fikkie/__init__.py
fikkie/check.py
fikkie/commands.py
fikkie/config.py
fikkie/main.py
fikkie/watchdog.py
fikkie/notifiers/__init__.py
fikkie/notifiers/base.py
fikkie/notifiers/discord.py
fikkie/notifiers/email.py
fikkie/notifiers/slack.py
fikkie/notifiers/telegram.py
fikkie-0.5.4.data/scripts/fikkie
fikkie-0.5.4.dist-info/LICENSE.md
fikkie-0.5.4.dist-info/METADATA
fikkie-0.5.4.dist-info/WHEEL
fikkie-0.5.4.dist-info/top_level.txt
fikkie-0.5.4.dist-info/RECORD
