Metadata-Version: 2.1
Name: fikkie
Version: 0.5.4
Summary: The simplest tool for lightweight monitoring over SSH, compatible with all your favorite messengers.
Home-page: https://github.com/nootr/fikkie/
Author: Joris Hartog (@nootr)
License: MIT
Classifier: Development Status :: 4 - Beta
Classifier: Framework :: Celery
Classifier: Intended Audience :: System Administrators
Classifier: License :: OSI Approved :: MIT License
Classifier: Natural Language :: English
Classifier: Operating System :: MacOS
Classifier: Operating System :: POSIX
Classifier: Programming Language :: Python :: 3.8
Classifier: Programming Language :: Python :: 3.9
Classifier: Programming Language :: Python :: 3.10
Classifier: Programming Language :: Python :: 3.11
Classifier: Topic :: System :: Monitoring
License-File: LICENSE.md
Requires-Dist: celery ==5.3.6
Requires-Dist: PyYAML ==5.3.1
Requires-Dist: tinydb ==4.8.0
Requires-Dist: typing-extensions ==4.0.1
